setup.py
screencast/__init__.py
screencast.egg-info/PKG-INFO
screencast.egg-info/SOURCES.txt
screencast.egg-info/dependency_links.txt
screencast.egg-info/top_level.txt