Metadata-Version: 1.0
Name: screencast
Version: 1.2
Summary: A script to open your browser to an awesome page.
Home-page: https://github.com/zachwill/screencast
Author: Zach Williams
Author-email: hey@zachwill.com
License: Unlicense (a.k.a. Public Domain)
Keywords: screencast,import screencast
Platform: UNKNOWN
Classifier: Development Status :: 5 - Production/Stable
Classifier: Intended Audience :: Developers
Classifier: Natural Language :: English
Classifier: Operating System :: OS Independent
Classifier: Programming Language :: Python :: 2
Classifier: Topic :: Internet
Classifier: Topic :: Internet :: WWW/HTTP
